examples/__init__.py
examples/examples.py
examples/models/__init__.py
model_loads/__init__.py
model_loads/loads.py
model_loads/utils/__init__.py
model_loads/utils/exceptions.py
model_loads/utils/loads.py
model_loads/utils/model_type.py
model_loads/utils/utils.py
tests/__init__.py
tests/mnist.py
tests/test_loads.py
model_loads-0.3.dist-info/LICENSE.md
model_loads-0.3.dist-info/METADATA
model_loads-0.3.dist-info/WHEEL
model_loads-0.3.dist-info/top_level.txt
model_loads-0.3.dist-info/RECORD
