Metadata-Version: 2.1
Name: model-loads
Version: 0.3
Summary: Loads GPU or CPU pytorch models
Home-page: https://github.com/cwh94/model_loads
Author: cwh94
Author-email: chaowanghs@gmail.com
License-File: LICENSE.md
